aioeasywebdav/__init__.py
aioeasywebdav/client.py
aioeasywebdav-2.4.0.dist-info/DESCRIPTION.rst
aioeasywebdav-2.4.0.dist-info/METADATA
aioeasywebdav-2.4.0.dist-info/RECORD
aioeasywebdav-2.4.0.dist-info/WHEEL
aioeasywebdav-2.4.0.dist-info/entry_points.txt
aioeasywebdav-2.4.0.dist-info/metadata.json
aioeasywebdav-2.4.0.dist-info/top_level.txt
