Metadata-Version: 2.0
Name: aioeasywebdav
Version: 2.4.0
Summary: A straight-forward WebDAV client, ported from easywebdav to use aiohttp.
Home-page: https://gitlab.com/alelec/aioeasywebdav
Author: Andrew Leech
Author-email: andrew@alelec.net
License: ISC
Platform: UNKNOWN
Classifier: Development Status :: 4 - Beta
Classifier: Intended Audience :: Developers
Classifier: Programming Language :: Python :: 3.5
Requires-Dist: aiohttp
Requires-Dist: six
Requires-Dist: setuptools-scm
